iotawallet/__init__.py
iotawallet/wallet.py
iotawallet/gui/__init__.py
iotawallet/gui/history.py
iotawallet/gui/overview.py
iotawallet/gui/receive.py
iotawallet/gui/send.py
iotawallet/gui/worker.py
iotawallet/gui/wxapp.py
iotawallet-0.0.6.dist-info/DESCRIPTION.rst
iotawallet-0.0.6.dist-info/METADATA
iotawallet-0.0.6.dist-info/RECORD
iotawallet-0.0.6.dist-info/WHEEL
iotawallet-0.0.6.dist-info/entry_points.txt
iotawallet-0.0.6.dist-info/metadata.json
iotawallet-0.0.6.dist-info/top_level.txt
