Metadata-Version: 2.0
Name: iotawallet
Version: 0.0.6
Summary: Python implementation of an Iota Wallet
Home-page: https://github.com/scottbelden/iotawallet
Author: Scott Belden
Author-email: scottabelden@gmail.com
License: MIT
Platform: UNKNOWN
Classifier: Intended Audience :: End Users/Desktop
Classifier: License :: OSI Approved :: MIT License
Classifier: Programming Language :: Python :: 3
Classifier: Programming Language :: Python :: 3.6
Requires-Dist: pyota
Requires-Dist: wxpython
